{
    "channels":  {
                     "cs":  {
                                "alias":  "19.03"
                            },
                     "19.03":  {
                                   "version":  "19.03.13-olljanat1"
                               }
                 },
    "versions":  {
                     "19.03.5-olljanat1":  {
                                     "date":  "2019-11-27T13:35:03",
                                     "url":  "https://github.com/olljanat/moby/releases/download/19.03.5-olljanat1/docker-19-03-5-olljanat1.zip",
                                     "size":  "128711618",
                                     "notes":  "Contains Docker EE for use with Windows Server.",
                                     "sha256":  "F79F6CE1EEE26B5A418CCBF325F82EF60A980CBAF823A1902324B2204FAB2679"
                                 },
                     "19.03.5-olljanat2":  {
                                    "date":  "2019-11-29T07:05:03",
                                    "url":  "https://github.com/olljanat/moby/releases/download/19.03.5-olljanat2/docker-19-03-5-olljanat2.zip",
                                    "size":  "128173189",
                                    "notes":  "Contains Docker EE for use with Windows Server.",
                                    "sha256":  "96F62CE77DF593649C1725492C85DE20345A7D8F804426707A5C1BE87FB57020"
                                },
                     "19.03.12-olljanat1":  {
                                    "date":  "2020-09-14T22:01:01",
                                    "url":  "https://github.com/olljanat/moby/releases/download/19.03.12-olljanat1/docker-19-03-12-olljanat1.zip",
                                    "size":  "77260680",
                                    "notes":  "Contains Docker EE for use with Windows Server.",
                                    "sha256":  "723666111F26BD6EF3772157CEFE432DD3A55192EB08827F38072483D0A8B0F7"
                                },
                     "19.03.13-olljanat1":  {
                                    "date":  "2020-10-26T11:50:01",
                                    "url":  "https://github.com/olljanat/moby/releases/download/19.03.13-olljanat1/docker-19-03-13-olljanat1.zip",
                                    "size":  "90159444",
                                    "notes":  "Contains Docker EE for use with Windows Server.",
                                    "sha256":  "31110CAD3BC5F0BA275FAD0052A74F0780EC6DD66BBA11BF756E2253EAEB386A"
                                }
                }
}
